{
  "number": 16489,
  "title": "Appel à projets \"L'enseignement agricole au service des transitions agroécologiques\"",
  "description": "L’appel à projets TAE+ a pour ambition de soutenir les initiatives des établissements qui contribuent de façon significative à la transition agroécologique.\r\nL'objectif est la mise en place et la diffusion d’innovations contribuant à améliorer significativement et collectivement le développement d'une agriculture agroécologique et multiperformante du point de vue économique, environnemental, sanitaire et social, en lien direct avec les autres acteurs du développement agricole et rural.\r\nLes champs d'investigations porteront à titre principal sur le \" Produire autrement (agricole et aquacole)\" et le \" Transformer, commercialiser, valoriser autrement\", mais également à titre complémentaire sur le \" Aménager autrement\" et le \" Proposer des services autrement\".",
  "tags": [

  ],
  "zones": [
    "Ministère de la Transition écologique et de la Cohésion des territoires"
  ],
  "datePublication": "2019-06-07T10:45:15+02:00",
  "service": {
    "nom": "Direction Générale de l'Enseignement et de la Recherche / Bureau du développement agricole et des partenariats pour l'innovation",
    "organisme": "Ministère de l'Agriculture et de l'Alimentation",
    "typeOrganisme": "administration_centrale"
  },
  "demarcheUrl": "https://www.demarches-simplifiees.fr/commencer/c845dcdb-860f-4196-849f-2a8011e5d6ff",
  "dpoUrl": null,
  "noticeUrl": null,
  "siteWebUrl": "",
  "cadreJuridiqueUrl": "http://agriculture.gouv.fr/developpement-agricole-et-rural-appels-projets",
  "logo": null,
  "notice": null,
  "deliberation": null,
  "dossiersCount": 0,
  "revision": {
    "champDescriptors": [
      {
        "__typename": "TextChampDescriptor",
        "label": "CELC - Etablissement chef de file",
        "description": "MAXIMUM : 50 caractères ",
        "required": true
      },
      {
        "__typename": "TextChampDescriptor",
        "label": "CPLL - Titre et acronyme du projet",
        "description": "MAXIMUM : 200 caractères",
        "required": true
      },
      {
        "__typename": "HeaderSectionChampDescriptor",
        "label": "CHEF DE PROJET",
        "description": "",
        "required": false
      },
      {
        "__typename": "TextChampDescriptor",
        "label": "NPCP - Nom, Prénom",
        "description": "",
        "required": true
      },
      {
        "__typename": "EmailChampDescriptor",
        "label": "EMCP - E-mail",
        "description": "",
        "required": true
      },
      {
        "__typename": "HeaderSectionChampDescriptor",
        "label": "PARTENARIAT",
        "description": "",
        "required": false
      },
      {
        "__typename": "TextChampDescriptor",
        "label": "NBPT - Liste des partenaires destinataires de financement CASDAR",
        "description": "Lister les partenaires en les séparant par une virgule.",
        "required": true
      },
      {
        "__typename": "TextChampDescriptor",
        "label": "Liste des autres partenaires (hors financements CASDAR)",
        "description": "Lister les partenaires en les séparant par une virgule.",
        "required": false
      },
      {
        "__typename": "HeaderSectionChampDescriptor",
        "label": "PROJET",
        "description": "",
        "required": false
      },
      {
        "__typename": "MultipleDropDownListChampDescriptor",
        "label": "Région(s) concernée(s)",
        "description": "Indiquer la(ou les) régions de l'ensemble des partenaires",
        "required": true,
        "options": [
          "Auvergne-Rhône-Alpes",
          "Bourgogne-Franche-Comté",
          "Bretagne",
          "Centre-Val de Loire",
          "Corse",
          "Grand Est",
          "Guadeloupe",
          "Guyane",
          "Hauts-de-France",
          "Île-de-France",
          "La Réunion",
          "Martinique",
          "Mayotte",
          "Normandie",
          "Nouvelle-Aquitaine",
          "Occitanie",
          "Pays de la Loire",
          "Provence-Alpes-Côte-d’Azur"
        ]
      },
      {
        "__typename": "MultipleDropDownListChampDescriptor",
        "label": "Champs d'investigation",
        "description": "Sélectionner le(s) champ(s) d'investigation correspondant au projet (choix multiple possible).",
        "required": true,
        "options": [
          "Produire autrement",
          "Transformer, commercialiser, valoriser autrement",
          "Aménager autrement",
          "Proposer des services autrement"
        ]
      },
      {
        "__typename": "TextChampDescriptor",
        "label": "Mots clés",
        "description": "Indiquer le (ou les) mot(s) clé(s) concernant le projet.",
        "required": true
      },
      {
        "__typename": "DateChampDescriptor",
        "label": "DTDB - Date de début du projet",
        "description": "",
        "required": true
      },
      {
        "__typename": "DateChampDescriptor",
        "label": "DTDF - Date de fin de projet",
        "description": "",
        "required": true
      },
      {
        "__typename": "NumberChampDescriptor",
        "label": "DRPR - Durée du projet",
        "description": "Saisir la durée en mois (42 mois maximum)",
        "required": true
      },
      {
        "__typename": "NumberChampDescriptor",
        "label": "Montant total des dépenses éligibles du projet",
        "description": "Saisir un nombre entier",
        "required": true
      },
      {
        "__typename": "NumberChampDescriptor",
        "label": "Montant de la subvention CASDAR demandée  pour le projet",
        "description": "Saisir un nombre entier",
        "required": true
      },
      {
        "__typename": "TextChampDescriptor",
        "label": "CPRS - Résumé du projet",
        "description": "MAXIMUM : 1000 caractères",
        "required": true
      },
      {
        "__typename": "HeaderSectionChampDescriptor",
        "label": "Pièces jointes",
        "description": "",
        "required": false
      },
      {
        "__typename": "PieceJustificativeChampDescriptor",
        "label": "DSTC - Descriptif du projet",
        "description": "Joindre l'Annexe I complétée AU FORMAT .PDF",
        "required": true
      },
      {
        "__typename": "PieceJustificativeChampDescriptor",
        "label": "PART - Budget prévisionnel et plan de financement",
        "description": "Joindre l'Annexe II complétée AU FORMAT .PDF INSCRIPTIBLE",
        "required": true
      },
      {
        "__typename": "PieceJustificativeChampDescriptor",
        "label": "FSPR - Fiche de synthèse du projet",
        "description": "Joindre l'Annexe III complétée AU FORMAT .DOC",
        "required": true
      },
      {
        "__typename": "ExplicationChampDescriptor",
        "label": "Attention ! Pour que votre dossier soit pris en compte, il est nécessaire de cliquer sur \"Soumettre le dossier\" après avoir complété tous les champs obligatoires et déposé les pièces jointes et ce, avant la clôture de la phase de dépôt (29 mai 2019 minuit). Les projets qui resteront au statut \"brouillon\" à cette date ne seront pas pris en compte lors de l'instruction.",
        "description": "",
        "required": false
      }
    ]
  }
}