{
  "number": 37070,
  "title": "FIPD 2021 - Sécurisation des établissements scolaires - Préfecture de la Haute-Garonne",
  "description": "SITE DE DÉPÔT DES DOSSIERS DE DEMANDE DE SUBVENTION DANS LE CADRE DU FONDS INTERMINISTÉRIEL DE PRÉVENTION DE LA DÉLINQUANCE (FIPD)\r\n\r\nVous avez besoin de votre numéro SIRET pour déposer votre demande de subvention.\r\n\r\nAssurez vous que les données qui y figurent soient à jour et correspondent bien à celles de votre RIB (adresse, dénomination de la structure).\r\n\r\nVous ne pouvez déposer qu'un projet à la fois.\r\n\r\nPour mémoire, le taux de subventions publiques applicable ne peut excéder 80 % du coût final de chaque projet (toutes subventions publiques confondues).\r\n\r\nLes trames des documents sont disponibles sur cette plateforme ainsi que sur le site internet de la préfecture de la Haute-Garonne. Pour les télécharger, suivre le lien ci-dessous :\r\nhttp://www.haute-garonne.gouv.fr/Politiques-publiques/Securite-et-protection-des-personnes-et-des-biens/Securite-interieure/Campagnes-de-prevention\r\n\r\n- Pour toute demande relative à la plateforme Démarches simplifiées, merci de contacter le service assistance de la plateforme :\r\nhttps://www.demarches-simplifiees.fr/contact-admin\r\nhttps://faq.demarches-simplifiees.fr\r\n\r\n- Pour toute question relative à la demande de subvention :\r\nPréfecture de la Haute-Garonne\r\nDirection des Services du Cabinet et des sécurités\r\nService des politiques de sécurité et de prévention\r\npref-fipd@haute-garonne.gouv.fr\r\n05 34 45 37 61 / 05 34 45 33 61",
  "tags": [

  ],
  "zones": [
    "Ministère de l'Intérieur et des Outre-mer"
  ],
  "datePublication": "2020-12-18T10:38:28+01:00",
  "service": {
    "nom": "Service des politiques de sécurité et de prévention (SP2)",
    "organisme": "Préfecture de la Haute-Garonne",
    "typeOrganisme": "service_deconcentre_de_l_etat"
  },
  "demarcheUrl": "https://www.demarches-simplifiees.fr/commencer/fipd2021-hg-securisation-des-etablissements-scolaires",
  "dpoUrl": null,
  "noticeUrl": null,
  "siteWebUrl": "http://www.haute-garonne.gouv.fr/Politiques-publiques/Securite-et-protection-des-personnes-et-des-biens/Securite-interieure/Campagnes-de-prevention",
  "cadreJuridiqueUrl": "",
  "logo": {
    "filename": "procedure-f4452c61-a094-4f49-967d-5ff98a5daadc.png",
    "checksum": "hF7J7i3VB3tbh+ZRSePmQQ==",
    "byteSize": "31717",
    "contentType": "image/png"
  },
  "notice": null,
  "deliberation": null,
  "dossiersCount": 43,
  "revision": {
    "champDescriptors": [
      {
        "__typename": "DropDownListChampDescriptor",
        "label": "Type de porteur",
        "description": null,
        "required": true,
        "options": [
          "Commune",
          "EPCI",
          "Association",
          "Autre"
        ],
        "otherOption": false
      },
      {
        "__typename": "TextChampDescriptor",
        "label": "Nom du porteur de projet",
        "description": null,
        "required": true
      },
      {
        "__typename": "TextChampDescriptor",
        "label": "Nom de l'établissement scolaire",
        "description": "",
        "required": true
      },
      {
        "__typename": "DropDownListChampDescriptor",
        "label": "Secteur",
        "description": null,
        "required": true,
        "options": [
          "Public",
          "Privé",
          "Sous contrat"
        ],
        "otherOption": false
      },
      {
        "__typename": "TextChampDescriptor",
        "label": "Adresse du site concerné",
        "description": "Adresse du site concerné par les travaux de sécurisation.",
        "required": true
      },
      {
        "__typename": "DropDownListChampDescriptor",
        "label": "Travaux de sécurisation",
        "description": "",
        "required": true,
        "options": [
          "Vidéoprotection",
          "Dispositifs de sécurisation autres que vidéoprotection",
          "Les 2"
        ],
        "otherOption": false
      },
      {
        "__typename": "ExplicationChampDescriptor",
        "label": "RIB",
        "description": "Une version scannée de votre RIB vous sera également demandée en PJ (à la fin du formulaire).",
        "required": false
      },
      {
        "__typename": "TextChampDescriptor",
        "label": "BANQUE",
        "description": "En majuscules.",
        "required": true
      },
      {
        "__typename": "IbanChampDescriptor",
        "label": "IBAN",
        "description": "En majuscules.",
        "required": true
      },
      {
        "__typename": "TextChampDescriptor",
        "label": "BIC",
        "description": "En majuscules.",
        "required": true
      },
      {
        "__typename": "TextChampDescriptor",
        "label": "TITULAIRE DU COMPTE",
        "description": "En majuscules.",
        "required": true
      },
      {
        "__typename": "HeaderSectionChampDescriptor",
        "label": "Contacts",
        "description": "",
        "required": false
      },
      {
        "__typename": "TextChampDescriptor",
        "label": "Nom du responsable du projet",
        "description": "Cette personne  sera l'interlocuteur privilégié des services de l’État, des collectivités territoriales et le cas échéant d'autres co-financeurs sollicités.",
        "required": true
      },
      {
        "__typename": "TextChampDescriptor",
        "label": "Prénom",
        "description": "",
        "required": true
      },
      {
        "__typename": "TextChampDescriptor",
        "label": "Fonction du responsable du projet",
        "description": "",
        "required": true
      },
      {
        "__typename": "EmailChampDescriptor",
        "label": "Mail du responsable du projet",
        "description": "",
        "required": true
      },
      {
        "__typename": "PhoneChampDescriptor",
        "label": "Numéro de téléphone du responsable du projet",
        "description": "",
        "required": true
      },
      {
        "__typename": "HeaderSectionChampDescriptor",
        "label": "Dispositifs de sécurité existants",
        "description": null,
        "required": false
      },
      {
        "__typename": "CheckboxChampDescriptor",
        "label": "Vidéoprotection",
        "description": "",
        "required": false
      },
      {
        "__typename": "NumberChampDescriptor",
        "label": "Nombre de caméras",
        "description": null,
        "required": false
      },
      {
        "__typename": "TextChampDescriptor",
        "label": "Date d'installation de ces caméras",
        "description": "",
        "required": false
      },
      {
        "__typename": "CheckboxChampDescriptor",
        "label": "Portail",
        "description": null,
        "required": false
      },
      {
        "__typename": "CheckboxChampDescriptor",
        "label": "Barrières",
        "description": null,
        "required": false
      },
      {
        "__typename": "CheckboxChampDescriptor",
        "label": "Clôture",
        "description": null,
        "required": false
      },
      {
        "__typename": "CheckboxChampDescriptor",
        "label": "Porte blindée",
        "description": null,
        "required": false
      },
      {
        "__typename": "CheckboxChampDescriptor",
        "label": "Vidéophone",
        "description": null,
        "required": false
      },
      {
        "__typename": "CheckboxChampDescriptor",
        "label": "Filtres anti-flagrants pour les fenêtres et barreaudage en RDC",
        "description": null,
        "required": false
      },
      {
        "__typename": "CheckboxChampDescriptor",
        "label": "Alarme spécifique d'alerte \"attentat-intrusion\" (différente de l'alarme incendie)",
        "description": null,
        "required": false
      },
      {
        "__typename": "CheckboxChampDescriptor",
        "label": "Mesures de protection des espaces de confinement (blocage des portes, protections balistiques, etc)",
        "description": null,
        "required": false
      },
      {
        "__typename": "TextChampDescriptor",
        "label": "Autres :",
        "description": "A préciser.",
        "required": false
      },
      {
        "__typename": "HeaderSectionChampDescriptor",
        "label": "Diagnostic de sûreté",
        "description": null,
        "required": false
      },
      {
        "__typename": "YesNoChampDescriptor",
        "label": "Plan Particulier de Mise en Sûreté (PPMS) actualisé au risque terroriste",
        "description": "Merci de joindre l'attestation selon laquelle le PPMS attentat/intrusion est à jour (exercices effectués) à la fin du formulaire (dans la rubrique \"Pièces jointes à transmettre\").",
        "required": true
      },
      {
        "__typename": "YesNoChampDescriptor",
        "label": "Consultation des référents sûreté de la police ou de la gendarmerie",
        "description": null,
        "required": true
      },
      {
        "__typename": "TextChampDescriptor",
        "label": "Si réponse \"oui\", merci de préciser le nom du référent intervenu et la date de la consultation.",
        "description": "Merci également de joindre le diagnostic de sûreté établi à la fin du formulaire (dans la rubrique \"Pièces jointes à transmettre\").",
        "required": false
      },
      {
        "__typename": "TextareaChampDescriptor",
        "label": "Description des défaillances repérées dans le dispositif :",
        "description": null,
        "required": true
      },
      {
        "__typename": "HeaderSectionChampDescriptor",
        "label": "Description des travaux à réaliser",
        "description": null,
        "required": false
      },
      {
        "__typename": "ExplicationChampDescriptor",
        "label": "Sécurisation périmétrique des bâtiments",
        "description": null,
        "required": false
      },
      {
        "__typename": "CheckboxChampDescriptor",
        "label": "Vidéoprotection",
        "description": null,
        "required": false
      },
      {
        "__typename": "NumberChampDescriptor",
        "label": "Nombre de caméras",
        "description": null,
        "required": false
      },
      {
        "__typename": "TextChampDescriptor",
        "label": "Finalité du dispositif et emplacement des caméras",
        "description": "Merci de décrire la finalité du dispositif et l'emplacement des caméras (un plan indiquant l'implantation et le champ de vision des caméras déjà existantes et des caméras souhaitées sera à joindre dans la rubrique \"Pièces jointes à transmettre\").",
        "required": false
      },
      {
        "__typename": "CheckboxChampDescriptor",
        "label": "Portail",
        "description": null,
        "required": false
      },
      {
        "__typename": "CheckboxChampDescriptor",
        "label": "Barrières",
        "description": null,
        "required": false
      },
      {
        "__typename": "CheckboxChampDescriptor",
        "label": "Clôture (création, renforcement, rehaussement)",
        "description": null,
        "required": false
      },
      {
        "__typename": "CheckboxChampDescriptor",
        "label": "Porte blindée",
        "description": null,
        "required": false
      },
      {
        "__typename": "CheckboxChampDescriptor",
        "label": "Vidéophone",
        "description": null,
        "required": false
      },
      {
        "__typename": "CheckboxChampDescriptor",
        "label": "Filtres anti-flagrants pour les fenêtres et barreaudage en RDC",
        "description": null,
        "required": false
      },
      {
        "__typename": "TextChampDescriptor",
        "label": "Autres :",
        "description": "A préciser.",
        "required": false
      },
      {
        "__typename": "ExplicationChampDescriptor",
        "label": "Sécurisation volumétrique des bâtiments",
        "description": null,
        "required": false
      },
      {
        "__typename": "CheckboxChampDescriptor",
        "label": "Alarme spécifique d'alerte \"attentat-intrusion\" (différente de l'alarme incendie)",
        "description": null,
        "required": false
      },
      {
        "__typename": "CheckboxChampDescriptor",
        "label": "Mesures de protection des espaces de confinement (blocage des portes, protections balistiques, etc)",
        "description": null,
        "required": false
      },
      {
        "__typename": "TextChampDescriptor",
        "label": "Autres :",
        "description": "A préciser.",
        "required": false
      },
      {
        "__typename": "TextareaChampDescriptor",
        "label": "Planning de réalisation des travaux :",
        "description": "A détailler.",
        "required": true
      },
      {
        "__typename": "HeaderSectionChampDescriptor",
        "label": "Budget",
        "description": null,
        "required": false
      },
      {
        "__typename": "NumberChampDescriptor",
        "label": "Coût total du projet (HT)",
        "description": "Préciser ici le coût total du budget HT du projet. Par ailleurs, le devis établi par un prestataire de service (daté et signé) vous sera également demandé en PJ (à la fin du formulaire).",
        "required": true
      },
      {
        "__typename": "YesNoChampDescriptor",
        "label": "Travaux réalisés en régie",
        "description": null,
        "required": true
      },
      {
        "__typename": "NumberChampDescriptor",
        "label": "Si réponse \"oui\", merci de préciser le coût",
        "description": null,
        "required": false
      },
      {
        "__typename": "NumberChampDescriptor",
        "label": "Montant de la subvention FIPD sollicitée",
        "description": "",
        "required": true
      },
      {
        "__typename": "TextareaChampDescriptor",
        "label": "Si taux de subvention sollicité supérieur à 50% : préciser les raisons pour lesquelles une subvention de 50% est demandée",
        "description": "Vulnérabilité particulière, antécédents, fragilité financière du porteur, etc.",
        "required": false
      },
      {
        "__typename": "TextareaChampDescriptor",
        "label": "Autres subventions sollicitées pour la réalisation du projet (le cas échéant).",
        "description": "Préciser les financeurs sollicités, le montant de subvention demandé et si celui-ci est prévisionnel ou acquis.",
        "required": false
      },
      {
        "__typename": "NumberChampDescriptor",
        "label": "Part d’autofinancement (en euros).",
        "description": null,
        "required": true
      },
      {
        "__typename": "ExplicationChampDescriptor",
        "label": "Subventions antérieures",
        "description": "Indiquer si des opérations de sécurisation ont été financées pour cette même structure par le FIPD auparavant.",
        "required": false
      },
      {
        "__typename": "TextareaChampDescriptor",
        "label": "Montant des aides obtenues :",
        "description": "Année par année.",
        "required": false
      },
      {
        "__typename": "TextareaChampDescriptor",
        "label": "Type de travaux réalisés :",
        "description": null,
        "required": false
      },
      {
        "__typename": "HeaderSectionChampDescriptor",
        "label": "Compléments",
        "description": "",
        "required": false
      },
      {
        "__typename": "TextareaChampDescriptor",
        "label": "Information complémentaire éventuelle",
        "description": "Cette rubrique vous permet d'apporter des précisions complémentaires susceptibles d'éclairer davantage les financeurs sur la pertinence de votre projet.",
        "required": false
      },
      {
        "__typename": "HeaderSectionChampDescriptor",
        "label": "Déclaration",
        "description": "",
        "required": false
      },
      {
        "__typename": "TextChampDescriptor",
        "label": "Nom du représentant légal",
        "description": "",
        "required": true
      },
      {
        "__typename": "TextChampDescriptor",
        "label": "Prénom du représentant légal",
        "description": "",
        "required": true
      },
      {
        "__typename": "TextChampDescriptor",
        "label": "Fonction du représentant légal",
        "description": "",
        "required": true
      },
      {
        "__typename": "EmailChampDescriptor",
        "label": "Adresse mail du représentant légal",
        "description": "",
        "required": true
      },
      {
        "__typename": "TextChampDescriptor",
        "label": "Adresse de correspondance",
        "description": null,
        "required": true
      },
      {
        "__typename": "CheckboxChampDescriptor",
        "label": "Attestation sur l'honneur",
        "description": "J'atteste être le (la) représentant(e) légal(e) de la structure, ou être autorisé(e) pour celui-ci à déposer cette demande de subvention.\nJe certifie que la structure est régulièrement déclarée, qu'elle est en règle au regard de l’ensemble des déclarations sociales et fiscales ainsi que des cotisations et paiements correspondants ; certifie exactes et sincères les informations du présent dossier, notamment la mention de l’ensemble des demandes de subventions introduites auprès d’autres financeurs publics ainsi que l’approbation du budget par les instances statutaires.\nJe précise que cette subvention, si elle est accordée, devra être versée au compte bancaire ou postal de la structure (RIB joint).\n\nATTENTION\n\nToute fausse déclaration est passible de peines d’emprisonnement et d’amendes prévues par les articles 4441-6 et 441-7 du code pénal.\nLe droit d’accès aux informations prévues par la loi n°78-17 du 6 janvier 1978 relative à l’informatique, aux fichiers et aux libertés s’exerce auprès du service ou de l’établissement auprès duquel vous avez déposé votre dossier.",
        "required": true
      },
      {
        "__typename": "HeaderSectionChampDescriptor",
        "label": "Pièces jointes à transmettre",
        "description": null,
        "required": false
      },
      {
        "__typename": "PieceJustificativeChampDescriptor",
        "label": "Cerfa de demande de subvention",
        "description": "Complété, daté et signé (valable aussi pour les établissements publics).\nPour les collectivités territoriales, ne compléter que les rubriques 1, 6 et 7.",
        "required": true
      },
      {
        "__typename": "PieceJustificativeChampDescriptor",
        "label": "Attestation PPMS actualisé au risque terroriste",
        "description": "Attestation du porteur de projet selon laquelle le ou les établissements visés disposent bien d’un PPMS actualisé au risque attentat-intrusion (ne pas envoyer les PPMS complets).",
        "required": true
      },
      {
        "__typename": "PieceJustificativeChampDescriptor",
        "label": "Plan d'implantation des caméras",
        "description": "En cas de vidéoprotection, merci de joindre un plan indiquant l'implantation et le champ de vision des caméras déjà existantes et des caméras souhaitées.",
        "required": false
      },
      {
        "__typename": "PieceJustificativeChampDescriptor",
        "label": "Copie du cerfa de demande d'autorisation préfectorale pour l'installation du système de vidéoprotection",
        "description": "En cas de vidéoprotection.",
        "required": false
      },
      {
        "__typename": "PieceJustificativeChampDescriptor",
        "label": "Devis établi par un prestataire de service, daté et signé",
        "description": null,
        "required": true
      },
      {
        "__typename": "PieceJustificativeChampDescriptor",
        "label": "Devis établi par un prestataire de service, daté et signé",
        "description": null,
        "required": false
      },
      {
        "__typename": "PieceJustificativeChampDescriptor",
        "label": "Diagnostic du référent sûreté (s'il a été réalisé)",
        "description": null,
        "required": false
      },
      {
        "__typename": "PieceJustificativeChampDescriptor",
        "label": "Attestation précisant le montant des dépenses et recettes annuelles",
        "description": "Pour les établissements privés sous contrat.",
        "required": false
      },
      {
        "__typename": "PieceJustificativeChampDescriptor",
        "label": "Relevé d'identité bancaire (RIB)",
        "description": "",
        "required": true
      },
      {
        "__typename": "RepetitionChampDescriptor",
        "label": "Autre document que vous jugez utile à votre demande",
        "description": null,
        "required": false,
        "champDescriptors": [
          {
            "__typename": "PieceJustificativeChampDescriptor",
            "label": "Merci de joindre toute pièce complémentaire qui vous paraîtrait utile.",
            "description": null,
            "required": false
          }
        ]
      }
    ]
  }
}